upydevice/__init__.py
upydevice/bledevice.py
upydevice/decorators.py
upydevice/devgroup.py
upydevice/devtools.py
upydevice/exceptions.py
upydevice/phantom.py
upydevice/phantom_wr.py
upydevice/serialdevice.py
upydevice/upydevice.py
upydevice/websocketdevice.py
upydevice/wsclient.py
upydevice/wsprotocol.py
upydevice-0.3.8.dist-info/LICENSE
upydevice-0.3.8.dist-info/METADATA
upydevice-0.3.8.dist-info/WHEEL
upydevice-0.3.8.dist-info/top_level.txt
upydevice-0.3.8.dist-info/RECORD
